alumath/__init__.py
alumath/matrix.py
alumath-1.0.0.dist-info/licenses/LICENCE
tests/__init__.py
tests/test_matrix.py
alumath-1.0.0.dist-info/METADATA
alumath-1.0.0.dist-info/WHEEL
alumath-1.0.0.dist-info/top_level.txt
alumath-1.0.0.dist-info/RECORD
