Metadata-Version: 2.4
Name: alumath
Version: 1.0.0
Summary: A simple Python library for matrix multiplication
Home-page: https://github.com/yourusername/alumath
Author: Group 3
Author-email: Your Name <your.email@example.com>
License: MIT
Classifier: Development Status :: 4 - Beta
Classifier: Intended Audience :: Developers
Classifier: License :: OSI Approved :: MIT License
Classifier: Operating System :: OS Independent
Classifier: Programming Language :: Python :: 3
Requires-Python: >=3.6
License-File: LICENCE
Dynamic: author
Dynamic: home-page
Dynamic: license-file
Dynamic: requires-python
